00_src/data_mem.sv
module data_mem(
    input logic         i_clk,
    input logic         i_rst_n,
    input logic         i_lsu_wren,
    input logic [2:0]   i_func3,
    input logic [31:0]  i_lsu_addr,
    input logic [31:0]  i_st_data,
    
    output logic [31:0] o_dmem_data
);

// == Func3, opcode

localparam [2:0] SB = 3'b000,
                 SH = 3'b001,
                 SW = 3'b010;
localparam [2:0] LB = 3'b000,
                 LH = 3'b001,
                 LW = 3'b010,
                 LBU = 3'b100,
                 LHU = 3'b101;
// == veriable
logic [15:0] temp_addr;
assign temp_addr = i_lsu_addr[15:0];
logic [7:0] temp_data [3:0];

// localparam D_MEM_SIZE = 8192;
localparam D_MEM_SIZE = 1000;
logic [7:0] dmem [D_MEM_SIZE - 1:0];
longint i = 0;

localparam [15:0] dmem_addr = 16'h2000,
                  end_addr  = 16'h3FFF;

always_ff @(posedge i_clk or negedge i_rst_n) begin : proc_store_data
    if(~(i_rst_n)) begin
        for(i = 0; i < D_MEM_SIZE; i++) begin
            dmem[i] = 8'h0;
        end
    end else begin
        if((i_lsu_wren == 1'b1) && ((i_lsu_addr[15:12] == 4'h2) | (i_lsu_addr[15:12] == 4'h3))) begin
            case (i_func3[1:0])
                2'b00: begin // Byte
                    if(temp_addr <= end_addr) dmem[temp_addr] <= i_st_data[7:0];
                end
                2'b01: begin // Half
                    if(temp_addr <= end_addr) dmem[temp_addr] <= i_st_data[7:0];
                    if(temp_addr + 1 <= end_addr) dmem[temp_addr + 1] <= i_st_data[15:8];
                end
                2'b10: begin // Word
                    if(temp_addr <= end_addr) dmem[temp_addr] <= i_st_data[7:0];
                    if(temp_addr + 1 <= end_addr) dmem[temp_addr + 1] <= i_st_data[15:8];
                    if(temp_addr + 2 <= end_addr) dmem[temp_addr + 2] <= i_st_data[23:16];
                    if(temp_addr + 3 <= end_addr) dmem[temp_addr + 3] <= i_st_data[31:24];
                end
            endcase
        end
    end
end

always_comb begin : proc_check_out_data
    if(temp_addr <= end_addr) temp_data[0] = dmem[temp_addr];
    else temp_data[0] = 8'h0;

    if(temp_addr + 1 <= end_addr) temp_data[1] = dmem[temp_addr + 1];
    else temp_data[1] = 8'h0;

    if(temp_addr + 2 <= end_addr) temp_data[2] = dmem[temp_addr + 2];
    else temp_data[2] = 8'h0;

    if(temp_addr + 3 <= end_addr) temp_data[3] = dmem[temp_addr + 3];
    else temp_data[3] = 8'h0;
end

always_comb begin : proc_load_data
    case(i_func3)
        LB: o_dmem_data = {{24{temp_data[0][7]}}, temp_data[0]};
        LH: o_dmem_data = {{16{temp_data[1][7]}}, temp_data[1], temp_data[0]};
        LW: o_dmem_data = {temp_data[3], temp_data[2], temp_data[1], temp_data[0]};
        LBU: o_dmem_data = {24'h0, temp_data[0]};
        LHU: o_dmem_data = {16'h0, temp_data[1], temp_data[0]};
        default: o_dmem_data = 32'hz;
    endcase
end
endmodule

quartus/output_buf.sv
module output_buf(
    input logic         i_clk,
    input logic         i_rst_n,
    input logic         i_lsu_wren,
    input logic [2:0]   i_func3,
    input logic [31:0]  i_lsu_addr,
    input logic [31:0]  i_output_buf_data,

    output logic [31:0] o_output_buf_data,
    output logic [31:0] o_io_ledr,
    output logic [31:0] o_io_ledg,
    output logic [6:0]  o_io_hex0,
    output logic [6:0]  o_io_hex1,
    output logic [6:0]  o_io_hex2,
    output logic [6:0]  o_io_hex3,
    output logic [6:0]  o_io_hex4,
    output logic [6:0]  o_io_hex5,
    output logic [6:0]  o_io_hex6,
    output logic [6:0]  o_io_hex7,
    output logic [31:0] o_io_lcd
);

// == Addr
localparam O_BUF_SIZE = 64;
logic [7:0] out_buf [O_BUF_SIZE - 1:0];

// == Func3 
localparam [2:0] LB  = 3'b000,
                 LH  = 3'b001,
                 LW  = 3'b010,
                 LBU = 3'b100,
                 LHU = 3'b101;

// == Memory mapping
localparam [7:0]  ledr_addr  = 8'h00,
                  ledg_addr  = 8'h10,
                  hex0_addr  = 8'h20,
                  hex1_addr  = 8'h21,
                  hex2_addr  = 8'h22,
                  hex3_addr  = 8'h23,
                  hex4_addr  = 8'h24,
                  hex5_addr  = 8'h25,
                  hex6_addr  = 8'h26,
                  hex7_addr  = 8'h27,
                  lcd_addr   = 8'h30,
                  end_addr   = 8'hFF;
assign o_io_ledr = {out_buf[ledr_addr + 3], out_buf[ledr_addr + 2], out_buf[ledr_addr + 1], out_buf[ledr_addr]};
assign o_io_ledg = {out_buf[ledg_addr + 3], out_buf[ledg_addr + 2], out_buf[ledg_addr + 1], out_buf[ledg_addr]};
assign o_io_hex0 = out_buf[hex0_addr][6:0];
assign o_io_hex1 = out_buf[hex1_addr][6:0];
assign o_io_hex2 = out_buf[hex2_addr][6:0];
assign o_io_hex3 = out_buf[hex3_addr][6:0];
assign o_io_hex4 = out_buf[hex4_addr][6:0];
assign o_io_hex5 = out_buf[hex5_addr][6:0];
assign o_io_hex6 = out_buf[hex6_addr][6:0];
assign o_io_hex7 = out_buf[hex7_addr][6:0];
assign o_io_lcd  = {out_buf[lcd_addr + 3], out_buf[lcd_addr + 2], out_buf[lcd_addr + 1], out_buf[lcd_addr]};

// == veriable
logic [7:0] temp_data [3:0];
logic [7:0] temp_addr;
assign temp_addr = i_lsu_addr[7:0] & 8'hFE;

always_comb begin : proc_check_out_data
    if(temp_addr <= end_addr) temp_data[0] = out_buf[temp_addr];
    else temp_data[0] = 8'h00;

    if(temp_addr + 1 <= end_addr) temp_data[1] = out_buf[temp_addr + 1];
    else temp_data[1] = 8'h00;

    if(temp_addr + 2 <= end_addr) temp_data[2] = out_buf[temp_addr + 2];
    else temp_data[2] = 8'h00;

    if(temp_addr + 3 <= end_addr) temp_data[3] = out_buf[temp_addr + 3];
    else temp_data[3] = 8'h00;    
end

always_comb begin : proc_select_opcode
    o_output_buf_data = 32'hz; // Gán giá trị mặc định
    case (i_func3)
        LB: begin
            if (i_lsu_addr[7:0] <= end_addr)
                o_output_buf_data = {{24{out_buf[i_lsu_addr[7:0]][7]}}, out_buf[i_lsu_addr[7:0]]};
        end
        LH: o_output_buf_data = {{16{temp_data[1][7]}}, temp_addr[1], temp_data[0]};
        LW: o_output_buf_data = {temp_data[3], temp_data[2], temp_data[1], temp_data[0]};
        LBU: begin
            if (i_lsu_addr[7:0] <= end_addr)
                o_output_buf_data = {24'h0, out_buf[i_lsu_addr[7:0]]};
            else
                o_output_buf_data = 32'h0;
        end
        LHU: o_output_buf_data = {16'h0, temp_data[1], temp_data[0]};
        default: o_output_buf_data = 32'hz;
    endcase
end

always_ff @( posedge i_clk or negedge i_rst_n ) begin : proc_output_buf
    if(~(i_rst_n)) begin
        out_buf[ledr_addr]      <= 8'h0;
        out_buf[ledr_addr + 1]  <= 8'h0;
        out_buf[ledr_addr + 2]  <= 8'h0;
        out_buf[ledr_addr + 3]  <= 8'h0;
        out_buf[ledg_addr]      <= 8'h0;
        out_buf[ledg_addr + 1]  <= 8'h0;
        out_buf[hex0_addr]      <= 8'h0;
        out_buf[hex1_addr]      <= 8'h0;
        out_buf[hex2_addr]      <= 8'h0;
        out_buf[hex3_addr]      <= 8'h0;
        out_buf[hex4_addr]      <= 8'h0;
        out_buf[hex5_addr]      <= 8'h0;
        out_buf[hex6_addr]      <= 8'h0;
        out_buf[hex7_addr]      <= 8'h0;
        out_buf[lcd_addr]       <= 8'h0;
        out_buf[lcd_addr + 1]   <= 8'h0;
        out_buf[lcd_addr + 2]   <= 8'h0;
        out_buf[lcd_addr + 3]   <= 8'h0;
    end else begin
        if((i_lsu_wren == 1'b1) && (i_lsu_addr[15:8] == 8'h70) ) begin // cho phep ghi 
            case (i_func3[1:0])
                2'b00: begin // Byte
                    if(i_lsu_addr[7:0] <= end_addr) out_buf[i_lsu_addr[7:0]] = i_output_buf_data[7:0];
                end
                2'b01: begin // Half
                    if(temp_addr <= end_addr) out_buf[temp_addr] = i_output_buf_data[7:0];
                    if(temp_addr + 1 <= end_addr) out_buf[temp_addr + 1] = i_output_buf_data[15:8]; 
                end
                2'b10: begin // Word
                    if(temp_addr <= end_addr)     out_buf[temp_addr]     = i_output_buf_data[7:0];
                    if(temp_addr + 1 <= end_addr) out_buf[temp_addr + 1] = i_output_buf_data[15:8];
                    if(temp_addr + 2 <= end_addr) out_buf[temp_addr + 2] = i_output_buf_data[23:16];
                    if(temp_addr + 3 <= end_addr) out_buf[temp_addr + 3] = i_output_buf_data[31:24];
                end
            endcase
        end
    end
end

endmodule

00_src/input_buf.sv
module input_buf(
    input logic [2:0]   i_func3,
    input logic [31:0]  i_lsu_addr,
    input logic [31:0]  i_io_sw,
    input logic [3:0]   i_io_btn,

    output logic [31:0] o_input_buf_data
);

// == Addr
localparam I_BUF_SIZE = 32; // 00 -> 1F
logic [7:0] in_buf [I_BUF_SIZE - 1:0];

// == Func3
localparam [2:0] SB = 3'b000,
                 SH = 3'b001,
                 SW = 3'b010;

// == Memory mapping
localparam [7:0]  sw_addr  = 8'h00,
                  btn_addr = 8'h10,
                  end_addr = 8'h1F;

assign in_buf[sw_addr]     = i_io_sw[7:0];
assign in_buf[sw_addr + 1] = i_io_sw[15:8];
assign in_buf[sw_addr + 2] = i_io_sw[23:16];
assign in_buf[sw_addr + 3] = i_io_sw[31:24];
assign in_buf[btn_addr]    = {4'h0, i_io_btn};

// == Veriable
logic [7:0] temp_data [3:0];
logic [7:0] temp_addr;
assign temp_addr = i_lsu_addr[7:0] & 8'hFE;

always_comb begin
    if(temp_addr <= end_addr) temp_data[0] = in_buf[temp_addr];
    else temp_data[0] = 8'h00;

    if((temp_addr + 1) <= end_addr) temp_data[1] = in_buf[temp_addr + 1];
    else temp_data[1] = 8'h00;

    if((temp_addr + 2) <= end_addr) temp_data[2] = in_buf[temp_addr + 2];
    else temp_data[2] = 8'h00;

    if((temp_addr + 3) <= end_addr) temp_data[3] = in_buf[temp_addr + 3];
    else temp_data[3] = 8'h00;
end

// == out data
always_comb begin
    case (i_func3)
        SB: o_input_buf_data = {24'b0, temp_data[0]};
        SH: o_input_buf_data = {16'b0, temp_data[1], temp_data[0]};
        SW: o_input_buf_data = {temp_data [3], temp_data[2], temp_data[1], temp_data[0]};
        default: o_input_buf_data = 32'hz;
    endcase
end

endmodule

quartus/lsu.sv
module lsu(
    input logic         i_clk,
    input logic         i_rst_n,
    input logic         i_lsu_wren,
    input logic [31:0]  i_lsu_addr,
    input logic [31:0]  i_st_data,
    input logic [31:0]  i_instr,

    input logic [3:0]   i_io_btn,
    input logic [31:0]  i_io_sw,

    output logic [6:0]  o_io_hex0,
    output logic [6:0]  o_io_hex1,
    output logic [6:0]  o_io_hex2,
    output logic [6:0]  o_io_hex3,
    output logic [6:0]  o_io_hex4,
    output logic [6:0]  o_io_hex5,
    output logic [6:0]  o_io_hex6,
    output logic [6:0]  o_io_hex7,
    
    output logic [31:0] o_ld_data,
    output logic [31:0] o_io_ledr,
    output logic [31:0] o_io_ledg,
    output logic [31:0] o_io_lcd
);

logic [31:0] r_input_data, r_output_data, r_dmem_data;

always_comb begin : proc_lsu
    if (~(|(i_lsu_addr[15:12] ^ 4'h2))) begin // dmem_buffer
        o_ld_data = r_dmem_data;
    end else if(~(|(i_lsu_addr[15:8] ^ 8'h78))) begin // input buffer
        o_ld_data = r_input_data;
    end else if(~(|(i_lsu_addr[15:8] ^ 8'h70))) begin // output buffer
        o_ld_data = r_output_data;
    end else begin
        o_ld_data = 32'hz;
    end
end

input_buf input_buf(
    .i_func3            (i_instr[14:12]),
    .i_lsu_addr         (i_lsu_addr),
    .i_io_sw            (i_io_sw),
    .i_io_btn           (i_io_btn),
    .o_input_buf_data   (r_input_data)
);

output_buf output_buf(
    .i_clk              (i_clk),
    .i_rst_n            (i_rst_n),
    .i_lsu_wren         (i_lsu_wren),
    .i_func3            (i_instr[14:12]),
    .i_lsu_addr         (i_lsu_addr),
    .i_output_buf_data  (i_st_data),
    .o_output_buf_data  (r_output_data),
    .o_io_ledr          (o_io_ledr),
    .o_io_ledg          (o_io_ledg),
    .o_io_hex0          (o_io_hex0),
    .o_io_hex1          (o_io_hex1),
    .o_io_hex2          (o_io_hex2),
    .o_io_hex3          (o_io_hex3),
    .o_io_hex4          (o_io_hex4),
    .o_io_hex5          (o_io_hex5),
    .o_io_hex6          (o_io_hex6),
    .o_io_hex7          (o_io_hex7),
    .o_io_lcd           (o_io_lcd )
);

data_mem dmem(
    .i_clk              (i_clk),
    .i_rst_n            (i_rst_n),
    .i_lsu_wren         (i_lsu_wren),
    .i_func3            (i_instr[14:12]),
    .i_lsu_addr         (i_lsu_addr),
    .i_st_data          (i_st_data),
    .o_dmem_data        (r_dmem_data)
);

endmodule

02_test/lsu_tb/lsu_tb.sv
`timescale 1ns/1ps
module lsu_tb;

    logic clk, rst_n;
    logic lsu_wren;
    logic [31:0] i_lsu_addr, i_st_data, i_instr, i_io_sw;
    logic [3:0] i_io_btn;
    logic [6:0] o_io_hex0, o_io_hex1, o_io_hex2, o_io_hex3, o_io_hex4, o_io_hex5, o_io_hex6, o_io_hex7;
    logic [31:0] o_ld_data, o_io_ledr, o_io_ledg, o_io_lcd;

    // Khởi tạo module DUT (Device Under Test)
    lsu uut(
        .i_clk       (clk         ),
        .i_rst_n     (rst_n       ),
        .i_lsu_wren  (lsu_wren    ),
        .i_lsu_addr  (i_lsu_addr  ),
        .i_st_data   (i_st_data   ),
        .i_instr     (i_instr     ),
        .i_io_btn    (i_io_btn    ),
        .i_io_sw     (i_io_sw     ),
        .o_io_hex0   (o_io_hex0   ),
        .o_io_hex1   (o_io_hex1   ),
        .o_io_hex2   (o_io_hex2   ),
        .o_io_hex3   (o_io_hex3   ),
        .o_io_hex4   (o_io_hex4   ),
        .o_io_hex5   (o_io_hex5   ),
        .o_io_hex6   (o_io_hex6   ),
        .o_io_hex7   (o_io_hex7   ),
        .o_ld_data   (o_ld_data   ),
        .o_io_ledr   (o_io_ledr   ),
        .o_io_ledg   (o_io_ledg   ),
        .o_io_lcd    (o_io_lcd    )
    );

    // Tạo clock (xung nhịp 10ns)
    always #5 clk = ~clk;

    initial begin
        $dumpfile("lsu_wave.vcd");
        $dumpvars(0, lsu_tb);
    end

    initial begin
        // Reset hệ thống
        clk     = 0;
        rst_n   = 0;
        lsu_wren = 0;
        i_lsu_addr = 0;
        i_st_data  = 0;
        i_instr    = 0;
        i_io_sw    = 0;
        i_io_btn   = 0;
        
        #20 rst_n = 1; // Bỏ reset sau 20ns

        // Kiểm tra store vào dmem
        #10 lsu_wren = 1;
        i_lsu_addr  = 32'h2000; // Địa chỉ trong dmem
        i_st_data   = 32'h2909;
        #10 lsu_wren = 0; // Dừng ghi

        // Kiểm tra load từ dmem
        #10 i_lsu_addr = 32'h2000;
        #10;
        $display("LOAD/STORE: %s", o_ld_data == 32'h2909 ? "PASS" : "FAIL");

        // Kiểm tra đọc i_io_sw (0x7800 - 0x780F)
        #10 i_io_sw = 32'h12345678;
        i_lsu_addr = 32'h7800;
        #10 ;
        $display("SW: %s", o_ld_data == 32'h12345678 ? "PASS" : "FAIL");

        // Kiểm tra đọc i_io_btn (0x7810 - 0x781F)
        #10 i_io_btn = 4'b1010;
        i_lsu_addr = 32'h7810;
        #10;
        $display("BTN: %s", o_ld_data[3:0] == 4'b1010 ? "PASS" : "FAIL");

        // Kiểm tra ghi vào HEX display (0x7020 - 0x7027)
        #10 lsu_wren = 1;
        i_lsu_addr = 32'h7020;
        i_st_data  = 32'h0F0F0F0F;
        #10 lsu_wren = 0;
        #10;
        $display("HEX DISPLAY: %s", (o_io_hex0 == 7'h0F && o_io_hex1 == 7'h0F) ? "PASS" : "FAIL");

        // Kiểm tra ghi vào LEDG (0x7010 - 0x701F)
        #10 lsu_wren = 1;
        i_lsu_addr = 32'h7010;
        i_st_data  = 32'h55AA55AA;
        #10 lsu_wren = 0;
        #10;
        $display("LEDG: %s", o_io_ledg == 32'h55AA55AA ? "PASS" : "FAIL");

        // Kiểm tra ghi vào LEDR (0x7000 - 0x700F)
        #10 lsu_wren = 1;
        i_lsu_addr = 32'h7000;
        i_st_data  = 32'hFF00FF00;
        #10 lsu_wren = 0;
        #10;
        $display("LEDR: %s", o_io_ledr == 32'hFF00FF00 ? "PASS" : "FAIL");

        // Kiểm tra ghi vào LCD (0x7030 - 0x703F)
        #10 lsu_wren = 1;
        i_lsu_addr = 32'h7030;
        i_st_data  = 32'hCAFEBABE;
        #10 lsu_wren = 0;
        #10;
        $display("LCD: %s", o_io_lcd == 32'hCAFEBABE ? "PASS" : "FAIL");

        // Kết thúc mô phỏng
        #20;
        $finish;
    end

endmodule

02_test/lsu_tb/lsu_wave.vcd
$version Generated by VerilatedVcd $end
$timescale 1ps $end
 $scope module TOP $end
  $scope module lsu_tb $end
   $var wire 1 i clk $end
   $var wire 1 # rst_n $end
   $var wire 1 $ lsu_wren $end
   $var wire 32 % i_lsu_addr [31:0] $end
   $var wire 32 & i_st_data [31:0] $end
   $var wire 32 ' i_instr [31:0] $end
   $var wire 32 ( i_io_sw [31:0] $end
   $var wire 4 ) i_io_btn [3:0] $end
   $var wire 7 \ o_io_hex0 [6:0] $end
   $var wire 7 ] o_io_hex1 [6:0] $end
   $var wire 7 ^ o_io_hex2 [6:0] $end
   $var wire 7 _ o_io_hex3 [6:0] $end
   $var wire 7 ` o_io_hex4 [6:0] $end
   $var wire 7 a o_io_hex5 [6:0] $end
   $var wire 7 b o_io_hex6 [6:0] $end
   $var wire 7 c o_io_hex7 [6:0] $end
   $var wire 32 j o_ld_data [31:0] $end
   $var wire 32 d o_io_ledr [31:0] $end
   $var wire 32 e o_io_ledg [31:0] $end
   $var wire 32 f o_io_lcd [31:0] $end
   $scope module uut $end
    $var wire 1 i i_clk $end
    $var wire 1 # i_rst_n $end
    $var wire 1 $ i_lsu_wren $end
    $var wire 32 % i_lsu_addr [31:0] $end
    $var wire 32 & i_st_data [31:0] $end
    $var wire 32 ' i_instr [31:0] $end
    $var wire 4 ) i_io_btn [3:0] $end
    $var wire 32 ( i_io_sw [31:0] $end
    $var wire 7 \ o_io_hex0 [6:0] $end
    $var wire 7 ] o_io_hex1 [6:0] $end
    $var wire 7 ^ o_io_hex2 [6:0] $end
    $var wire 7 _ o_io_hex3 [6:0] $end
    $var wire 7 ` o_io_hex4 [6:0] $end
    $var wire 7 a o_io_hex5 [6:0] $end
    $var wire 7 b o_io_hex6 [6:0] $end
    $var wire 7 c o_io_hex7 [6:0] $end
    $var wire 32 j o_ld_data [31:0] $end
    $var wire 32 d o_io_ledr [31:0] $end
    $var wire 32 e o_io_ledg [31:0] $end
    $var wire 32 f o_io_lcd [31:0] $end
    $var wire 32 - r_input_data [31:0] $end
    $var wire 32 R r_output_data [31:0] $end
    $var wire 32 S r_dmem_data [31:0] $end
    $scope module dmem $end
     $var wire 1 i i_clk $end
     $var wire 1 # i_rst_n $end
     $var wire 1 $ i_lsu_wren $end
     $var wire 3 * i_func3 [2:0] $end
     $var wire 32 % i_lsu_addr [31:0] $end
     $var wire 32 & i_st_data [31:0] $end
     $var wire 32 S o_dmem_data [31:0] $end
     $var wire 3 k SB [2:0] $end
     $var wire 3 l SH [2:0] $end
     $var wire 3 m SW [2:0] $end
     $var wire 3 k LB [2:0] $end
     $var wire 3 l LH [2:0] $end
     $var wire 3 m LW [2:0] $end
     $var wire 3 n LBU [2:0] $end
     $var wire 3 o LHU [2:0] $end
     $var wire 16 + temp_addr [15:0] $end
     $var wire 8 T temp_data[0] [7:0] $end
     $var wire 8 U temp_data[1] [7:0] $end
     $var wire 8 V temp_data[2] [7:0] $end
     $var wire 8 W temp_data[3] [7:0] $end
     $var wire 32 p D_MEM_SIZE [31:0] $end
     $var wire 64 g i [63:0] $end
     $var wire 16 q dmem_addr [15:0] $end
     $var wire 16 r end_addr [15:0] $end
    $upscope $end
    $scope module input_buf $end
     $var wire 3 * i_func3 [2:0] $end
     $var wire 32 % i_lsu_addr [31:0] $end
     $var wire 32 ( i_io_sw [31:0] $end
     $var wire 4 ) i_io_btn [3:0] $end
     $var wire 32 - o_input_buf_data [31:0] $end
     $var wire 32 s I_BUF_SIZE [31:0] $end
     $var wire 8 . in_buf[0] [7:0] $end
     $var wire 8 / in_buf[1] [7:0] $end
     $var wire 8 0 in_buf[2] [7:0] $end
     $var wire 8 1 in_buf[3] [7:0] $end
     $var wire 8 2 in_buf[4] [7:0] $end
     $var wire 8 3 in_buf[5] [7:0] $end
     $var wire 8 4 in_buf[6] [7:0] $end
     $var wire 8 5 in_buf[7] [7:0] $end
     $var wire 8 6 in_buf[8] [7:0] $end
     $var wire 8 7 in_buf[9] [7:0] $end
     $var wire 8 8 in_buf[10] [7:0] $end
     $var wire 8 9 in_buf[11] [7:0] $end
     $var wire 8 : in_buf[12] [7:0] $end
     $var wire 8 ; in_buf[13] [7:0] $end
     $var wire 8 < in_buf[14] [7:0] $end
     $var wire 8 = in_buf[15] [7:0] $end
     $var wire 8 > in_buf[16] [7:0] $end
     $var wire 8 ? in_buf[17] [7:0] $end
     $var wire 8 @ in_buf[18] [7:0] $end
     $var wire 8 A in_buf[19] [7:0] $end
     $var wire 8 B in_buf[20] [7:0] $end
     $var wire 8 C in_buf[21] [7:0] $end
     $var wire 8 D in_buf[22] [7:0] $end
     $var wire 8 E in_buf[23] [7:0] $end
     $var wire 8 F in_buf[24] [7:0] $end
     $var wire 8 G in_buf[25] [7:0] $end
     $var wire 8 H in_buf[26] [7:0] $end
     $var wire 8 I in_buf[27] [7:0] $end
     $var wire 8 J in_buf[28] [7:0] $end
     $var wire 8 K in_buf[29] [7:0] $end
     $var wire 8 L in_buf[30] [7:0] $end
     $var wire 8 M in_buf[31] [7:0] $end
     $var wire 3 k SB [2:0] $end
     $var wire 3 l SH [2:0] $end
     $var wire 3 m SW [2:0] $end
     $var wire 8 t sw_addr [7:0] $end
     $var wire 8 u btn_addr [7:0] $end
     $var wire 8 v end_addr [7:0] $end
     $var wire 8 N temp_data[0] [7:0] $end
     $var wire 8 O temp_data[1] [7:0] $end
     $var wire 8 P temp_data[2] [7:0] $end
     $var wire 8 Q temp_data[3] [7:0] $end
     $var wire 8 , temp_addr [7:0] $end
    $upscope $end
    $scope module output_buf $end
     $var wire 1 i i_clk $end
     $var wire 1 # i_rst_n $end
     $var wire 1 $ i_lsu_wren $end
     $var wire 3 * i_func3 [2:0] $end
     $var wire 32 % i_lsu_addr [31:0] $end
     $var wire 32 & i_output_buf_data [31:0] $end
     $var wire 32 R o_output_buf_data [31:0] $end
     $var wire 32 d o_io_ledr [31:0] $end
     $var wire 32 e o_io_ledg [31:0] $end
     $var wire 7 \ o_io_hex0 [6:0] $end
     $var wire 7 ] o_io_hex1 [6:0] $end
     $var wire 7 ^ o_io_hex2 [6:0] $end
     $var wire 7 _ o_io_hex3 [6:0] $end
     $var wire 7 ` o_io_hex4 [6:0] $end
     $var wire 7 a o_io_hex5 [6:0] $end
     $var wire 7 b o_io_hex6 [6:0] $end
     $var wire 7 c o_io_hex7 [6:0] $end
     $var wire 32 f o_io_lcd [31:0] $end
     $var wire 32 w O_BUF_SIZE [31:0] $end
     $var wire 3 k LB [2:0] $end
     $var wire 3 l LH [2:0] $end
     $var wire 3 m LW [2:0] $end
     $var wire 3 n LBU [2:0] $end
     $var wire 3 o LHU [2:0] $end
     $var wire 8 t ledr_addr [7:0] $end
     $var wire 8 u ledg_addr [7:0] $end
     $var wire 8 x hex0_addr [7:0] $end
     $var wire 8 y hex1_addr [7:0] $end
     $var wire 8 z hex2_addr [7:0] $end
     $var wire 8 { hex3_addr [7:0] $end
     $var wire 8 | hex4_addr [7:0] $end
     $var wire 8 } hex5_addr [7:0] $end
     $var wire 8 ~ hex6_addr [7:0] $end
     $var wire 8 !! hex7_addr [7:0] $end
     $var wire 8 "! lcd_addr [7:0] $end
     $var wire 8 #! end_addr [7:0] $end
     $var wire 8 X temp_data[0] [7:0] $end
     $var wire 8 Y temp_data[1] [7:0] $end
     $var wire 8 Z temp_data[2] [7:0] $end
     $var wire 8 [ temp_data[3] [7:0] $end
     $var wire 8 , temp_addr [7:0] $end
    $upscope $end
   $upscope $end
  $upscope $end
 $upscope $end
$enddefinitions $end


#0
0#
0$
b00000000000000000000000000000000 %
b00000000000000000000000000000000 &
b00000000000000000000000000000000 '
b00000000000000000000000000000000 (
b0000 )
b000 *
b0000000000000000 +
b00000000 ,
b00000000000000000000000000000000 -
b00000000 .
b00000000 /
b00000000 0
b00000000 1
b00000000 2
b00000000 3
b00000000 4
b00000000 5
b00000000 6
b00000000 7
b00000000 8
b00000000 9
b00000000 :
b00000000 ;
b00000000 <
b00000000 =
b00000000 >
b00000000 ?
b00000000 @
b00000000 A
b00000000 B
b00000000 C
b00000000 D
b00000000 E
b00000000 F
b00000000 G
b00000000 H
b00000000 I
b00000000 J
b00000000 K
b00000000 L
b00000000 M
b00000000 N
b00000000 O
b00000000 P
b00000000 Q
b00000000000000000000000000000000 R
b00000000000000000000000000000000 S
b00000000 T
b00000000 U
b00000000 V
b00000000 W
b00000000 X
b00000000 Y
b00000000 Z
b00000000 [
b0000000 \
b0000000 ]
b0000000 ^
b0000000 _
b0000000 `
b0000000 a
b0000000 b
b0000000 c
b00000000000000000000000000000000 d
b00000000000000000000000000000000 e
b00000000000000000000000000000000 f
b0000000000000000000000000000000000000000000000000000000000000000 g
0i
b00000000000000000000000000000000 j
b000 k
b001 l
b010 m
b100 n
b101 o
b00000000000000000000001111101000 p
b0010000000000000 q
b0011111111111111 r
b00000000000000000000000000100000 s
b00000000 t
b00010000 u
b00011111 v
b00000000000000000000000001000000 w
b00100000 x
b00100001 y
b00100010 z
b00100011 {
b00100100 |
b00100101 }
b00100110 ~
b00100111 !!
b00110000 "!
b11111111 #!
#5000
b0000000000000000000000000000000000000000000000000000001111101000 g
1i
#10000
0i
#15000
1i
#20000
1#
0i
#25000
1i
#30000
1$
b00000000000000000010000000000000 %
b00000000000000000010100100001001 &
b0010000000000000 +
0i
#35000
b00000000000000000000000000001001 S
b00001001 T
1i
b00000000000000000000000000001001 j
#40000
0$
0i
#45000
1i
#50000
0i
#55000
1i
#60000
0i
#65000
1i
#70000
b00000000000000000111100000000000 %
b00010010001101000101011001111000 (
b0111100000000000 +
b00000000000000000000000001111000 -
b01111000 .
b01010110 /
b00110100 0
b00010010 1
b01111000 N
b01010110 O
b00110100 P
b00010010 Q
b00000000000000000000000000000000 S
b00000000 T
0i
b00000000000000000000000001111001 j
#75000
1i
#80000
0i
#85000
1i
#90000
b00000000000000000111100000010000 %
b1010 )
b0111100000010000 +
b00010000 ,
b00000000000000000000000000001010 -
b00001010 >
b00001010 N
b00000000 O
b00000000 P
b00000000 Q
0i
b00000000000000000000000000001011 j
#95000
1i
#100000
0i
#105000
1i
#110000
1$
b00000000000000000111000000100000 %
b00001111000011110000111100001111 &
b0111000000100000 +
b00100000 ,
b00000000000000000000000000000000 -
b00000000 N
0i
#115000
b00000000000000000000000000001111 R
b00001111 X
b0001111 \
1i
b00000000000000000000000000001111 j
#120000
0$
0i
#125000
1i
#130000
0i
#135000
1i
#140000
1$
b00000000000000000111000000010000 %
b01010101101010100101010110101010 &
b0111000000010000 +
b00010000 ,
b00000000000000000000000000001010 -
b00001010 N
b00000000000000000000000000000000 R
b00000000 X
0i
b00000000000000000000000000001011 j
#145000
b11111111111111111111111110101010 R
b10101010 X
b00000000000000000000000010101010 e
1i
b11111111111111111111111110101011 j
#150000
0$
0i
#155000
1i
#160000
0i
#165000
1i
#170000
1$
b00000000000000000111000000000000 %
b11111111000000001111111100000000 &
b0111000000000000 +
b00000000 ,
b00000000000000000000000001111000 -
b01111000 N
b01010110 O
b00110100 P
b00010010 Q
b00000000000000000000000000000000 R
b00000000 X
0i
b00000000000000000000000000001011 j
#175000
1i
#180000
0$
0i
#185000
1i
#190000
0i
#195000
1i
#200000
1$
b00000000000000000111000000110000 %
b11001010111111101011101010111110 &
b0111000000110000 +
b00110000 ,
b00000000000000000000000000000000 -
b00000000 N
b00000000 O
b00000000 P
b00000000 Q
0i
#205000
b11111111111111111111111110111110 R
b10111110 X
b00000000000000000000000010111110 f
1i
b11111111111111111111111110111111 j
#210000
0$
0i
