00_src/immgen.sv
module immgen(
    input logic [31:0]  i_instr,
    output logic [31:0] o_immgen
);

// OPCODE TYPES
localparam [4:0] R_type  = 5'b01100,
                 I_type  = 5'b00100,
                 S_type  = 5'b01000,
                 L_type  = 5'b00000,
                 SB_type = 5'b11000,
                 UL_type = 5'b01101,
                 UA_type = 5'b00101,
                 UJ_type = 5'b11011,
                 IJ_type = 5'b11001;  // JALR (I-Type format)

always_comb begin
    case (i_instr[6:2])
        R_type:  o_immgen = 32'b0;  // R-type has no immediate

        // I-type (ADDI, LW, JALR)
        I_type, L_type, IJ_type: 
            o_immgen = {{21{i_instr[31]}}, i_instr[30:20]};

        // S-type (SW, SH, SB)
        S_type:
            o_immgen = {{21{i_instr[31]}}, i_instr[30:25], i_instr[11:7]};

        // SB-type (BEQ, BNE, BLT, BGE, BLTU, BGEU)
        SB_type:
            o_immgen = {{20{i_instr[31]}}, i_instr[7], i_instr[30:25], i_instr[11:8], 1'b0};

        // U-type (LUI, AUIPC)
        UL_type, UA_type:
            o_immgen = {i_instr[31:12], 12'b0};

        // UJ-type (JAL)
        UJ_type:
            o_immgen = {{13{i_instr[20]}}, i_instr[10:1], i_instr[11], i_instr[19:12]};

        default:
            o_immgen = 32'b0;
    endcase
end

endmodule

02_test/imm_gen_tb/tb_immgen.sv
`timescale 1ns/1ps
module tb_immgen;

    // Testbench signals
    logic [31:0] i_instr;   // Input instruction
    logic [31:0] o_immgen;  // Output immediate value

    // Instantiate DUT (Device Under Test)
    immgen uut (
        .i_instr(i_instr),
        .o_immgen(o_immgen)
    );

    // Task to display results
    task check_result(input string test_name, input [31:0] expected);
        if (o_immgen === expected) begin
            $display("[%s] PASS: o_immgen = %0d (Expected = %0d)", test_name, o_immgen, expected);
        end else begin
            $display("[%s] FAIL: o_immgen = %0d (Expected = %0d)", test_name, o_immgen, expected);
        end
    endtask

    // Stimulus and checks
    initial begin
        $dumpfile("tb_immgen.vcd");
        $dumpvars(0, tb_immgen);

        // Test R-type (No Immediate)
        i_instr = 32'h00000033;  // Example R-type instruction
        #10;
        check_result("R-Type Test", 32'b0);

        // Test I-type (ADDI, LW, JALR)
        i_instr = 32'hFE320493;  // ADDI x9, x4, -29
        #10;
        check_result("I-Type Test", -29);

        i_instr = 32'h0294A203; // LW x4, 0x29(x9)
        #10;
        check_result("L-Type Test", 41);

        // Test S-type (SW, SH, SB)
        i_instr = 32'h00922EA3;  // sw x9, 29(x4)
        #10;
        check_result("S-Type Test", 29);

        // Test SB-type (BEQ, BNE, BLT, BGE, BLTU, BGEU)
        i_instr = 32'hFE4481E3;  // beq x9, x4, -30
        #10;
        check_result("SB-Type Test", -30);

        // Test U-type (LUI, AUIPC)
        i_instr = 32'h02909037;  // LUI x0, 0x2909
        #10;
        check_result("U-Type Test", 32'h02909000); // Correct expected value

        // Test UJ-type (JAL)
        i_instr = 32'h0280026F;  // JAL x0, 0x29
        #10;
        check_result("UJ-Type Test", {{13{1'b0}}, 10'b100110111, 1'b0, 8'b00000000});

        // Test IJ-type (JALR)
        i_instr = 32'h029204E7;  // JALR x9, x4, 29
        #10;
        check_result("IJ-Type Test", 41);

        $finish;
    end

endmodule

02_test/imm_gen_tb/tb_immgen.vcd
$version Generated by VerilatedVcd $end
$timescale 1ps $end
 $scope module TOP $end
  $scope module tb_immgen $end
   $var wire 32 # i_instr [31:0] $end
   $var wire 32 $ o_immgen [31:0] $end
   $scope module uut $end
    $var wire 32 # i_instr [31:0] $end
    $var wire 32 $ o_immgen [31:0] $end
    $var wire 5 % R_type [4:0] $end
    $var wire 5 & I_type [4:0] $end
    $var wire 5 ' S_type [4:0] $end
    $var wire 5 ( L_type [4:0] $end
    $var wire 5 ) SB_type [4:0] $end
    $var wire 5 * UL_type [4:0] $end
    $var wire 5 + UA_type [4:0] $end
    $var wire 5 , UJ_type [4:0] $end
    $var wire 5 - IJ_type [4:0] $end
   $upscope $end
  $upscope $end
 $upscope $end
$enddefinitions $end


#0
b00000000000000000000000000110011 #
b00000000000000000000000000000000 $
b01100 %
b00100 &
b01000 '
b00000 (
b11000 )
b01101 *
b00101 +
b11011 ,
b11001 -
#10000
b11111110001100100000010010010011 #
b11111111111111111111111111100011 $
#20000
b00000010100101001010001000000011 #
b00000000000000000000000000101001 $
#30000
b00000000100100100010111010100011 #
b00000000000000000000000000011101 $
#40000
b11111110010001001000000111100011 #
b11111111111111111111111111100010 $
#50000
b00000010100100001001000000110111 #
b00000010100100001001000000000000 $
#60000
b00000010100000000000001001101111 #
b00000000000000100110111000000000 $
#70000
b00000010100100100000010011100111 #
b00000000000000000000000000101001 $
